quantfin/macro/__init__.py
quantfin/macro/__version__.py
quantfin/macro/charts/__init__.py
quantfin/macro/charts/components_and_line_chart.py
quantfin/macro/charts/line_and_shade_chart.py
quantfin_macro-0.1.3.dist-info/LICENSE
quantfin_macro-0.1.3.dist-info/METADATA
quantfin_macro-0.1.3.dist-info/WHEEL
quantfin_macro-0.1.3.dist-info/RECORD
