Metadata-Version: 2.1
Name: quantfin-macro
Version: 0.1.3
Summary: QuantFin collection - Macro related utilities and functions
License: MIT
Author: Matteo Angeloni
Author-email: mattange@gmail.com
Maintainer: Matteo Angeloni
Maintainer-email: mattange@gmail.com
Requires-Python: >=3.11.0,<4.0.0
Classifier: License :: OSI Approved :: MIT License
Classifier: Programming Language :: Python :: 3
Classifier: Programming Language :: Python :: 3.11
Classifier: Programming Language :: Python :: 3.12
Classifier: Programming Language :: Python :: 3.13
Requires-Dist: great-tables (>=0.13.0,<0.14.0)
Requires-Dist: matplotlib (>=3.9.2,<4.0.0)
Requires-Dist: pandas (>=2.2.3,<3.0.0)
Requires-Dist: seaborn (>=0.13.2,<0.14.0)
